phant.py
phant-0.4.dist-info/RECORD
phant-0.4.dist-info/METADATA
phant-0.4.dist-info/DESCRIPTION.rst
phant-0.4.dist-info/top_level.txt
phant-0.4.dist-info/WHEEL
phant-0.4.dist-info/metadata.json
