Metadata-Version: 2.0
Name: phant
Version: 0.4
Summary: Client library for Sparkfun's Phant
Home-page: http://github.com/matze/python-phant
Author: Matthias Vogelgesang
Author-email: matthias.vogelgesang@gmail.com
License: UNKNOWN
Platform: UNKNOWN
Requires-Dist: requests
